{
  "categories": [
    {
      "id": 1,
      "tendm": "Cà phê"
    },
    {
      "id": 2,
      "tendm": "Trà"
    }
  ],
  "products": [
    {
      "id": 1,
      "tensp": "Đường Đen Sữa Đá",
      "gia": 49000,
      "category_id": 1,
      "hinh": "https://product.hstatic.net/1000075078/product/1737357048_uong-den-sua-da_5876b3829fe94af788996ca234a7894f_large.png"
    },
    {
      "id": 2,
      "tensp": "Bạc Xĩu",
      "gia": 20000,
      "category_id": 1,
      "hinh": "https://product.hstatic.net/1000075078/product/1737357020_bac-xiu-da_43a593b61b8e44379111a9ebb00904d9_large.png"
    },
    {
      "id": 3,
      "tensp": "The Coffee House Sữa Đá",
      "gia": 39000,
      "category_id": 1,
      "hinh": "https://product.hstatic.net/1000075078/product/1737357037_tch-sua-da_a83639744db94a7a96c1fd6b08e023e1_large.png"
    },
    {
      "id": 4,
      "tensp": "Bạc Xỉu Nóng",
      "gia": 39000,
      "category_id": 1,
      "hinh": "https://product.hstatic.net/1000075078/product/1737357029_bac-xiu-nong_e0a0732dee144dfda4e3cb43949ce065_large.png"
    },
    {
      "id": 5,
      "tensp": "Cà Phê Đen Nóng",
      "gia": 35000,
      "category_id": 1,
      "hinh": "https://product.hstatic.net/1000075078/product/1737356979_cf-den-nong_3ce91ffbdc04405b93855cd3b5d5aec2_large.png"
    },
    {
      "id": 6,
      "tensp": "Latte Almond",
      "gia": 59000,
      "category_id": 1,
      "hinh": "https://files.catbox.moe/5m1ltr.png"
    },
    {
      "id": 7,
      "tensp": "Latte Caramel",
      "gia": 59000,
      "category_id": 1,
      "hinh": "https://files.catbox.moe/isn6wi.png"
    },
    {
      "id": 8,
      "tensp": "Latte Hazelnut",
      "gia": 59000,
      "category_id": 1,
      "hinh": "https://files.catbox.moe/bgu6ln.png"
    },
    {
      "id": 9,
      "tensp": "Latte Coconut",
      "gia": 59000,
      "category_id": 1,
      "hinh": "https://files.catbox.moe/izdmgg.png"
    },
    {
      "id": 10,
      "tensp": "Latte Bạc Xỉu",
      "gia": 49000,
      "category_id": 1,
      "hinh": "https://files.catbox.moe/swrihi.png"
    },
    {
      "id": 11,
      "tensp": "Latte Classic",
      "gia": 55000,
      "category_id": 1,
      "hinh": "https://files.catbox.moe/nypx9w.png"
    },
    {
      "id": 12,
      "tensp": "Trà Sữa Oolong Nướng Sương Sáo",
      "gia": 55000,
      "category_id": 2,
      "hinh": "https://files.catbox.moe/h7ad5w.png"
    },
    {
      "id": 13,
      "tensp": "Trà Sữa Oolong Tứ Quý Sương Sáo",
      "gia": 55000,
      "category_id": 2,
      "hinh": "https://files.catbox.moe/vi4m1u.png"
    },
    {
      "id": 14,
      "tensp": "Hồng Trà Sữa Nóng",
      "gia": 55000,
      "category_id": 2,
      "hinh": "https://files.catbox.moe/oejvv8.png"
    },
    {
      "id": 15,
      "tensp": "Hồng Trà Sữa Trân Châu",
      "gia": 55000,
      "category_id": 2,
      "hinh": "https://files.catbox.moe/jggdzf.png"
    },
    {
      "id": 16,
      "tensp": "Trà Đen Macchiato",
      "gia": 55000,
      "category_id": 2,
      "hinh": "https://files.catbox.moe/zuax88.png"
    },
    {
      "id": 17,
      "tensp": "Trà Sữa Oolong BLao",
      "gia": 39000,
      "category_id": 2,
      "hinh": "https://files.catbox.moe/nly5t2.png"
    },
    {
      "id": 18,
      "tensp": "Hi-Tea Đào Kombucha",
      "gia": 59000,
      "category_id": 2,
      "hinh": "https://files.catbox.moe/qo6dbo.png"
    },
    {
      "id": 19,
      "tensp": "Hi-Tea Yuzu Kombucha",
      "gia": 59000,
      "category_id": 2,
      "hinh": "https://files.catbox.moe/zanqsv.png"
    },
    {
      "id": 20,
      "tensp": "Hi-Tea Yuzu Trân Châu",
      "gia": 49000,
      "category_id": 2,
      "hinh": "https://files.catbox.moe/4rj6ue.png"
    },
    {
      "id": 21,
      "tensp": "Hi-Tea Vải",
      "gia": 49000,
      "category_id": 2, 
      "hinh": "https://files.catbox.moe/o79y4a.png"
    },
    {
      "id": 22,
      "tensp": "Hi-Tea Đào",
      "gia": 49000,
      "category_id": 2,
      "hinh": "https://files.catbox.moe/5dlruz.png"
    }
  ],
  "sizes": [
    {
      "id": 1,
      "tensize": "S",
      "gia": 0
    },
    {
      "id": 2,
      "tensize": "M",
      "gia": 5000
    },
    {
      "id": 3,
      "tensize": "L",
      "gia": 10000
    }
  ]
}
